mseep_nagios_mcp-0.1.5.dist-info/licenses/LICENSE
nagios_mcp/__init__.py
nagios_mcp/__main__.py
nagios_mcp/server.py
nagios_mcp/tools/__init__.py
nagios_mcp/tools/config_tools.py
nagios_mcp/tools/status_tools.py
nagios_mcp/tools/tools.py
nagios_mcp/tools/utils.py
mseep_nagios_mcp-0.1.5.dist-info/METADATA
mseep_nagios_mcp-0.1.5.dist-info/WHEEL
mseep_nagios_mcp-0.1.5.dist-info/entry_points.txt
mseep_nagios_mcp-0.1.5.dist-info/top_level.txt
mseep_nagios_mcp-0.1.5.dist-info/RECORD
